accmt/__init__.py
accmt/callbacks.py
accmt/collate_fns.py
accmt/curriculum.py
accmt/dataloader_samplers.py
accmt/decorators.py
accmt/dist_utils.py
accmt/evaluator.py
accmt/hp_search.py
accmt/hyperparameters.py
accmt/metrics.py
accmt/model_wrapper.py
accmt/modules.py
accmt/monitor.py
accmt/states.py
accmt/tqdm.py
accmt/tracker.py
accmt/trainer.py
accmt/tunnel.py
accmt/utility.py
accmt/utils.py
accmt-1.9.3.dist-info/licenses/LICENSE
cli/__init__.py
cli/accmt.py
cli/launch.py
cli/parser.py
cli/utils.py
cli/config/ddp-bf16.yaml
cli/config/ddp-fp16.yaml
cli/config/ddp-fp32.yaml
cli/config/ddp-fp8.yaml
cli/config/ddp.yaml
cli/config/deepspeed-0-bf16.yaml
cli/config/deepspeed-0-fp16.yaml
cli/config/deepspeed-0-fp32.yaml
cli/config/deepspeed-0-fp8.yaml
cli/config/deepspeed-0.yaml
cli/config/deepspeed-1-bf16.yaml
cli/config/deepspeed-1-fp16.yaml
cli/config/deepspeed-1-fp32.yaml
cli/config/deepspeed-1-fp8.yaml
cli/config/deepspeed-1.yaml
cli/config/deepspeed-2-bf16-cpu-cpu.yaml
cli/config/deepspeed-2-bf16-cpu-none.yaml
cli/config/deepspeed-2-bf16-cpu-nvme.yaml
cli/config/deepspeed-2-bf16-none-cpu.yaml
cli/config/deepspeed-2-bf16-none-none.yaml
cli/config/deepspeed-2-bf16-none-nvme.yaml
cli/config/deepspeed-2-bf16-nvme-cpu.yaml
cli/config/deepspeed-2-bf16-nvme-none.yaml
cli/config/deepspeed-2-bf16-nvme-nvme.yaml
cli/config/deepspeed-2-bf16.yaml
cli/config/deepspeed-2-fp16-cpu-cpu.yaml
cli/config/deepspeed-2-fp16-cpu-none.yaml
cli/config/deepspeed-2-fp16-cpu-nvme.yaml
cli/config/deepspeed-2-fp16-none-cpu.yaml
cli/config/deepspeed-2-fp16-none-none.yaml
cli/config/deepspeed-2-fp16-none-nvme.yaml
cli/config/deepspeed-2-fp16-nvme-cpu.yaml
cli/config/deepspeed-2-fp16-nvme-none.yaml
cli/config/deepspeed-2-fp16-nvme-nvme.yaml
cli/config/deepspeed-2-fp16.yaml
cli/config/deepspeed-2-fp32-cpu-cpu.yaml
cli/config/deepspeed-2-fp32-cpu-none.yaml
cli/config/deepspeed-2-fp32-cpu-nvme.yaml
cli/config/deepspeed-2-fp32-none-cpu.yaml
cli/config/deepspeed-2-fp32-none-none.yaml
cli/config/deepspeed-2-fp32-none-nvme.yaml
accmt-1.9.3.dist-info/METADATA
accmt-1.9.3.dist-info/WHEEL
accmt-1.9.3.dist-info/entry_points.txt
accmt-1.9.3.dist-info/top_level.txt
accmt-1.9.3.dist-info/RECORD
