Metadata-Version: 2.4
Name: accmt
Version: 1.9.3
Summary: Accelerator Module and Trainer based on Accelerate library for simple distributed train processes, inspired by PyTorch Lightning.
Home-page: https://github.com/ghanvert/AcceleratorModule
Author: ghanvert
Author-email: martin.pizarro@cenia.cl
Project-URL: Bug Tracker, https://github.com/ghanvert/AcceleratorModule/issues
Classifier: Programming Language :: Python :: 3
Classifier: License :: OSI Approved :: Apache Software License
Classifier: Operating System :: OS Independent
Requires-Python: >=3.9
License-File: LICENSE
Requires-Dist: accelerate
Requires-Dist: numpy
Requires-Dist: PyYAML
Requires-Dist: pympler
Requires-Dist: numba
Requires-Dist: optuna
Dynamic: license-file
